databeakers/__init__.py
databeakers/_models.py
databeakers/_record.py
databeakers/_utils.py
databeakers/beakers.py
databeakers/cli.py
databeakers/config.py
databeakers/decorators.py
databeakers/edges.py
databeakers/exceptions.py
databeakers/http.py
databeakers/pipeline.py
databeakers/py.typed
databeakers-0.3.10.dist-info/METADATA
databeakers-0.3.10.dist-info/WHEEL
databeakers-0.3.10.dist-info/entry_points.txt
databeakers-0.3.10.dist-info/licenses/LICENSE
databeakers-0.3.10.dist-info/RECORD
