Metadata-Version: 2.4
Name: databeakers
Version: 0.3.10
Summary: Add your description here
License-File: LICENSE
Requires-Python: >=3.12
Requires-Dist: httpx>=0.28.1
Requires-Dist: networkx>=3.4.2
Requires-Dist: pydantic-settings>=2.9.1
Requires-Dist: pydantic>=2.11.5
Requires-Dist: pydot>=4.0.0
Requires-Dist: rich>=14.0.0
Requires-Dist: scrapelib>=2.3.0
Requires-Dist: sqlite-utils>=3.38
Requires-Dist: structlog>=25.3.0
Requires-Dist: toml>=0.10.2
Requires-Dist: typer>=0.15.4
